paas_extractor/__init__.py
paas_extractor/cli.py
paas_extractor/demo.py
paas_extractor/extractor.py
paas_extractor/test_suite.py
paas_extractor/data/biologic_injectables.csv
paas_extractor/data/eyedrop_beyond_use_dates.csv
paas_extractor/data/ftu_dosing_guide.csv
paas_extractor/data/injectable_diabetic_meds.csv
paas_extractor/data/insulin_pen_dosing_increments.csv
paas_extractor/data/insulin_products.csv
paas_extractor/data/nasal_inhalers.csv
paas_extractor/data/nonbiologic_injectables.csv
paas_extractor/data/oral_inhaler_products.csv
paas_extractor/data/pbm_eyedrop_guidelines.csv
paas_national_prescription_extractor-2.0.8.dist-info/licenses/LICENSE
paas_national_prescription_extractor-2.0.8.dist-info/METADATA
paas_national_prescription_extractor-2.0.8.dist-info/WHEEL
paas_national_prescription_extractor-2.0.8.dist-info/entry_points.txt
paas_national_prescription_extractor-2.0.8.dist-info/top_level.txt
paas_national_prescription_extractor-2.0.8.dist-info/RECORD
