Metadata-Version: 2.4
Name: paas-national-prescription-extractor
Version: 2.0.8
Summary: PAAS National - Comprehensive prescription data extraction and standardization system for day supply, quantity, and sig processing
Home-page: https://github.com/HalemoGPA/paas-national-prescription-extractor
Author: Abdulhaleem Osama
Author-email: Abdulhaleem Osama <haleemborham3@gmail.com>
Maintainer-email: TJMLabs <abdulhaleem@tjmlabs.com>
License: MIT
Project-URL: Homepage, https://github.com/HalemoGPA/paas-national-prescription-extractor
Project-URL: Documentation, https://github.com/HalemoGPA/paas-national-prescription-extractor/wiki
Project-URL: Repository, https://github.com/HalemoGPA/paas-national-prescription-extractor
Project-URL: Bug Reports, https://github.com/HalemoGPA/paas-national-prescription-extractor/issues
Keywords: pharmacy,prescription,healthcare,paas,day-supply,quantity,sig,medication,extraction
Classifier: Development Status :: 5 - Production/Stable
Classifier: Intended Audience :: Healthcare Industry
Classifier: Topic :: Scientific/Engineering :: Medical Science Apps.
Classifier: License :: OSI Approved :: MIT License
Classifier: Programming Language :: Python :: 3
Classifier: Programming Language :: Python :: 3.8
Classifier: Programming Language :: Python :: 3.9
Classifier: Programming Language :: Python :: 3.10
Classifier: Programming Language :: Python :: 3.11
Classifier: Programming Language :: Python :: 3.12
Classifier: Programming Language :: Python :: 3.13
Requires-Python: >=3.8
License-File: LICENSE
Requires-Dist: pandas>=1.5.0
Requires-Dist: numpy>=1.21.0
Requires-Dist: python-dateutil>=2.8.0
Requires-Dist: pytz>=2021.1
Requires-Dist: setuptools>=45.0
Dynamic: author
Dynamic: home-page
Dynamic: license-file
Dynamic: requires-python
